passgenpyNYU/__init__.py
passgenpyNYU/__main__.py
passgenpyNYU/core.py
passgenpynyu-1.1.0.dist-info/licenses/LICENSE
passgenpynyu-1.1.0.dist-info/METADATA
passgenpynyu-1.1.0.dist-info/WHEEL
passgenpynyu-1.1.0.dist-info/entry_points.txt
passgenpynyu-1.1.0.dist-info/top_level.txt
passgenpynyu-1.1.0.dist-info/RECORD
