Metadata-Version: 2.4
Name: passgenpyNYU
Version: 1.1.0
Summary: Generating serious and funny passwords.
Author-email: Jeffrey Chen <jc11711@nyu.edu>, Shaurya Srivastava <ss15635@nyu.edu>, Ethan Zheng <ez2146@nyu.edu>, Max Meyring <ml7751@nyu.edu>
License:                     GNU GENERAL PUBLIC LICENSE
Project-URL: Homepage, https://github.com/software-students-spring2025/3-python-package-ejsm
Project-URL: Repository, https://github.com/software-students-spring2025/3-python-package-ejsm
Keywords: python,package,build,tutorial
Classifier: Programming Language :: Python :: 3
Classifier: Intended Audience :: Education
Classifier: License :: OSI Approved :: GNU General Public License v3 (GPLv3)
Classifier: Operating System :: OS Independent
Requires-Python: >=3.7
License-File: LICENSE
Provides-Extra: dev
Requires-Dist: pytest; extra == "dev"
Dynamic: license-file
